HelloWorldDemo_colewilson/__init__.py
HelloWorldDemo_colewilson-0.0.1.data/scripts/hello
HelloWorldDemo_colewilson-0.0.1.dist-info/METADATA
HelloWorldDemo_colewilson-0.0.1.dist-info/WHEEL
HelloWorldDemo_colewilson-0.0.1.dist-info/entry_points.txt
HelloWorldDemo_colewilson-0.0.1.dist-info/top_level.txt
HelloWorldDemo_colewilson-0.0.1.dist-info/RECORD
